README.rst
setup.py
repi_client/__init__.py
repi_client/command_line.py
repi_client/pip_utils.py
repi_client/repi_client.py
repi_client.egg-info/PKG-INFO
repi_client.egg-info/SOURCES.txt
repi_client.egg-info/dependency_links.txt
repi_client.egg-info/entry_points.txt
repi_client.egg-info/not-zip-safe
repi_client.egg-info/requires.txt
repi_client.egg-info/top_level.txt